dicomselect/__init__.py
dicomselect/__version__.py
dicomselect/constants.py
dicomselect/convert.py
dicomselect/database.py
dicomselect/dicom.py
dicomselect/info.py
dicomselect/logger.py
dicomselect/query.py
dicomselect/queryfactory.py
dicomselect/reader.py
dicomselect/tags_generated.py
dicomselect-0.11.1.dist-info/LICENSE
dicomselect-0.11.1.dist-info/METADATA
dicomselect-0.11.1.dist-info/WHEEL
dicomselect-0.11.1.dist-info/top_level.txt
dicomselect-0.11.1.dist-info/RECORD
