Metadata-Version: 2.1
Name: dicomselect
Version: 0.11.1
Home-page: https://diagnijmegen.github.io/dicomselect/
Author-email: Stan.Noordman@radboudumc.nl
License: MIT License
Project-URL: GitHub, https://github.com/DIAGNijmegen/dicomselect
License-File: LICENSE
Requires-Dist: pydicom ~=2.3
Requires-Dist: SimpleITK ~=2.3
Requires-Dist: tqdm ~=4.65
Requires-Dist: pandas ~=2.0
Requires-Dist: pylibjpeg ~=2.0
Requires-Dist: pylibjpeg-libjpeg ~=2.2
Requires-Dist: rapidfuzz ~=3.0
Requires-Dist: python-Levenshtein ~=0.21
Requires-Dist: treelib ~=1.6
Provides-Extra: dev
Requires-Dist: pytest ; extra == 'dev'
Requires-Dist: flake8 ; extra == 'dev'
Requires-Dist: sphinx ; extra == 'dev'
